spiderbro/__init__.py
spiderbro/data/__init__.py
spiderbro/data/join_csvs.py
spiderbro-0.1.dist-info/METADATA
spiderbro-0.1.dist-info/WHEEL
spiderbro-0.1.dist-info/entry_points.txt
spiderbro-0.1.dist-info/top_level.txt
spiderbro-0.1.dist-info/RECORD
