Metadata-Version: 2.1
Name: spiderbro
Version: 0.1
Summary: tools and scripts for web scraping
Home-page: https://gitlab.com/granitosaurus/spiderbro
Author: Bernardas Ališauskas
Author-email: bernardas.alisauskas@pm.me
License: GPLv3
Platform: UNKNOWN
Requires-Dist: requests
Requires-Dist: click
